jesse_ftx/__init__.py
jesse_ftx-0.1.0.dist-info/LICENSE
jesse_ftx-0.1.0.dist-info/METADATA
jesse_ftx-0.1.0.dist-info/WHEEL
jesse_ftx-0.1.0.dist-info/top_level.txt
jesse_ftx-0.1.0.dist-info/RECORD
