Metadata-Version: 2.1
Name: jesse-ftx
Version: 0.1.0
Summary: FTX driver for Jesse framework
Home-page: https://jesse.trade
Author: Saleh Mir
Author-email: algo@hey.com
License: UNKNOWN
Project-URL: Documentation, https://docs.jesse.trade
Project-URL: Say Thanks!, http://jesse.trade/discord
Project-URL: Source, https://github.com/jesse-ai/ftx-driver
Project-URL: Tracker, https://github.com/jesse-ai/ftx-driver/issues
Platform: UNKNOWN
Classifier: Programming Language :: Python :: 3
Classifier: License :: OSI Approved :: MIT License
Classifier: Operating System :: OS Independent
Requires-Python: >=3.7
Requires-Dist: jesse
